quantumspectra_2024/__init__.py
quantumspectra_2024/common/Config.py
quantumspectra_2024/common/__init__.py
quantumspectra_2024/common/absorption/AbsorptionModel.py
quantumspectra_2024/common/absorption/AbsorptionSpectrum.py
quantumspectra_2024/common/absorption/__init__.py
quantumspectra_2024/common/hamiltonian/HamiltonianComputation.py
quantumspectra_2024/common/hamiltonian/HamiltonianModel.py
quantumspectra_2024/common/hamiltonian/__init__.py
quantumspectra_2024/models/__init__.py
quantumspectra_2024/models/mlj/MLJComputation.py
quantumspectra_2024/models/mlj/MLJModel.py
quantumspectra_2024/models/mlj/__init__.py
quantumspectra_2024/models/stark/StarkModel.py
quantumspectra_2024/models/stark/__init__.py
quantumspectra_2024/models/two_state/TwoStateComputation.py
quantumspectra_2024/models/two_state/TwoStateModel.py
quantumspectra_2024/models/two_state/__init__.py
quantumspectra_2024/scripts/__init__.py
quantumspectra_2024/scripts/qs_2024.py
quantumspectra_2024-0.1.5.dist-info/METADATA
quantumspectra_2024-0.1.5.dist-info/WHEEL
quantumspectra_2024-0.1.5.dist-info/entry_points.txt
quantumspectra_2024-0.1.5.dist-info/RECORD
