Metadata-Version: 2.1
Name: quantumspectra-2024
Version: 0.1.5
Summary: generates absorption spectra for donor-acceptor quantum systems
Author: benkoppe
Author-email: bentastic1@gmail.com
Requires-Python: >=3.10,<4.0
Classifier: Programming Language :: Python :: 3
Classifier: Programming Language :: Python :: 3.10
Classifier: Programming Language :: Python :: 3.11
Classifier: Programming Language :: Python :: 3.12
Requires-Dist: jax (>=0.4.25,<0.5.0)
Requires-Dist: jax-dataclasses (>=1.6.0,<2.0.0)
Requires-Dist: jaxtyping (>=0.2.28,<0.3.0)
Requires-Dist: matplotlib (>=3.8.3,<4.0.0)
Requires-Dist: numpy (>=1.26.4,<2.0.0)
